morpyneural/__init__.py
morpyneural/Genetic/ElementClass.py
morpyneural/Genetic/JitElementClass.py
morpyneural/Genetic/JitPopulationClass.py
morpyneural/Genetic/PopulationClass.py
morpyneural/Genetic/__init__.py
morpyneural/Math/JitMatrix.py
morpyneural/Math/PyMatrix.py
morpyneural/Math/__init__.py
morpyneural/Neural/JitLayerClass.py
morpyneural/Neural/JitNeuralNetworkClass.py
morpyneural/Neural/LayersClass.py
morpyneural/Neural/NeuralNetworkClass.py
morpyneural/Neural/__init__.py
morpyneural-0.0.2.dist-info/LICENSE
morpyneural-0.0.2.dist-info/METADATA
morpyneural-0.0.2.dist-info/WHEEL
morpyneural-0.0.2.dist-info/top_level.txt
morpyneural-0.0.2.dist-info/RECORD
